{
    "Group": "@ArcaneConduits",
    "DrawType": "Model",
    "Material": "Crystal",
    "Opacity": "Transparent",
    "CustomModel": "Blocks/ArcaneConduits/Mana_Crystal_Core.blockymodel",
    "CustomModelTexture": [
        {
            "Texture": "Blocks/ArcaneConduits/Mana_Crystal_Core.png",
            "Weight": 1
        }
    ],
    "CustomModelScale": 1.0,
    "Light": {
        "R": 150,
        "G": 80,
        "B": 255,
        "Intensity": 1.0
    },
    "BlockSoundSetId": "Crystal",
    "BlockParticleSetId": "Crystal",
    "ParticleColor": "#9650ff",
    "Flags": {},
    "Gathering": {
        "Hard": {
            "IsWeaponBreakable": false,
            "GatherType": "CrystalBlocks"
        }
    },
    "HitboxType": "FullBlock",
    "AmbientSoundEventId": "SFX_Crystal_Hum",
    "Looping": true,
    "InteractionHint": "server.interactionHints.toggle",
    "Interactions": {
        "Use": {
            "Interactions": [
                {
                    "Type": "ChangeState",
                    "Changes": {
                        "default": "inactive",
                        "inactive": "default"
                    }
                }
            ]
        }
    },
    "State": {
        "Type": "PowerSourceBlockState",
        "Data": {
            "OutputPower": 15,
            "Constant": true
        },
        "Definitions": {
            "inactive": {
                "InteractionHint": "server.interactionHints.activate",
                "Light": {
                    "R": 50,
                    "G": 25,
                    "B": 100,
                    "Intensity": 0.2
                },
                "Particles": null,
                "AmbientSoundEventId": null,
                "CustomModelTexture": [
                    {
                        "Texture": "Blocks/ArcaneConduits/Mana_Crystal_Core_Inactive.png",
                        "Weight": 1
                    }
                ]
            }
        }
    },
    "Particles": [
        {
            "SystemId": "Crystal_Energy_Pulse",
            "Scale": 1.0,
            "PositionOffset": {
                "Y": 0.5
            }
        }
    ]
}
